{
  "id": "3626698",
  "name": "梯子",
  "font_family": "iconfont",
  "css_prefix_text": "icon-",
  "description": "",
  "glyphs": [
    {
      "icon_id": "4848008",
      "name": "导出",
      "font_class": "daochu",
      "unicode": "e613",
      "unicode_decimal": 58899
    },
    {
      "icon_id": "5651338",
      "name": "导出",
      "font_class": "daochu1",
      "unicode": "e654",
      "unicode_decimal": 58964
    },
    {
      "icon_id": "57708",
      "name": "close",
      "font_class": "close",
      "unicode": "e62b",
      "unicode_decimal": 58923
    },
    {
      "icon_id": "109745",
      "name": "font",
      "font_class": "font",
      "unicode": "e620",
      "unicode_decimal": 58912
    },
    {
      "icon_id": "710408",
      "name": "template-default",
      "font_class": "templatedefault",
      "unicode": "e74a",
      "unicode_decimal": 59210
    },
    {
      "icon_id": "751444",
      "name": "扬声器_speaker76",
      "font_class": "yangshengqispeaker76",
      "unicode": "e637",
      "unicode_decimal": 58935
    },
    {
      "icon_id": "996191",
      "name": "img",
      "font_class": "img",
      "unicode": "e699",
      "unicode_decimal": 59033
    },
    {
      "icon_id": "1138742",
      "name": "close",
      "font_class": "close1",
      "unicode": "e644",
      "unicode_decimal": 58948
    },
    {
      "icon_id": "5354485",
      "name": "46-Ruler",
      "font_class": "-Ruler",
      "unicode": "e642",
      "unicode_decimal": 58946
    },
    {
      "icon_id": "7442356",
      "name": "pdf",
      "font_class": "pdf1",
      "unicode": "e759",
      "unicode_decimal": 59225
    },
    {
      "icon_id": "8291524",
      "name": "模版_fill",
      "font_class": "template_fill",
      "unicode": "e6c7",
      "unicode_decimal": 59079
    },
    {
      "icon_id": "8554642",
      "name": "markdown-fill",
      "font_class": "markdown-fill",
      "unicode": "e6b5",
      "unicode_decimal": 59061
    },
    {
      "icon_id": "8554646",
      "name": "markdown-line",
      "font_class": "markdown-line",
      "unicode": "e6b6",
      "unicode_decimal": 59062
    },
    {
      "icon_id": "11398862",
      "name": "eye",
      "font_class": "eye",
      "unicode": "e600",
      "unicode_decimal": 58880
    },
    {
      "icon_id": "11399242",
      "name": "ruler",
      "font_class": "ruler",
      "unicode": "e601",
      "unicode_decimal": 58881
    },
    {
      "icon_id": "11488246",
      "name": "default-template-fill",
      "font_class": "default-template-fill",
      "unicode": "e77c",
      "unicode_decimal": 59260
    },
    {
      "icon_id": "11686842",
      "name": "speaker_on",
      "font_class": "speaker_on",
      "unicode": "e67e",
      "unicode_decimal": 59006
    },
    {
      "icon_id": "18663433",
      "name": "闪电",
      "font_class": "shandian",
      "unicode": "e638",
      "unicode_decimal": 58936
    },
    {
      "icon_id": "19899604",
      "name": "template",
      "font_class": "template",
      "unicode": "e6ad",
      "unicode_decimal": 59053
    },
    {
      "icon_id": "21908989",
      "name": "accessibility",
      "font_class": "accessibility",
      "unicode": "e969",
      "unicode_decimal": 59753
    },
    {
      "icon_id": "22273895",
      "name": "ladder",
      "font_class": "ladder",
      "unicode": "e730",
      "unicode_decimal": 59184
    },
    {
      "icon_id": "22613456",
      "name": "闪电",
      "font_class": "shandian1",
      "unicode": "e634",
      "unicode_decimal": 58932
    },
    {
      "icon_id": "15838516",
      "name": "pdf",
      "font_class": "pdf",
      "unicode": "e67a",
      "unicode_decimal": 59002
    }
  ]
}
